.coveragerc
.editorconfig
.gitignore
.gitlab-ci.yml
.gitleaks.toml
AUTHORS.rst
CITATION
CODE_OF_CONDUCT.rst
CONTRIBUTING.rst
HISTORY.rst
LICENSE
MANIFEST.in
Makefile
README.rst
pyproject.toml
LICENSES/GPL-3.0-or-later.txt
docs/Makefile
docs/authors.rst
docs/conf.py
docs/contributing.rst
docs/history.rst
docs/index.html
docs/index.rst
docs/installation.rst
docs/make.bat
docs/readme.rst
docs/usage.rst
docs/_build/html/_static/file.png
docs/_build/html/_static/minus.png
docs/_build/html/_static/plus.png
docs/_static/custom.css
docs/images/screenshot_enfrosp_gui_v0.1.0.png
docs/images/screenshot_enfrosp_gui_v0.2.0.png
enfrosp_enmapboxapp/__init__.py
enfrosp_enmapboxapp/enfrosp_algorithm.py
enfrosp_enmapboxapp/enfrosp_enmapboxapp.py
enfrosp_enmapboxapp/version.py
enfrosp_enmapboxapp.egg-info/PKG-INFO
enfrosp_enmapboxapp.egg-info/SOURCES.txt
enfrosp_enmapboxapp.egg-info/dependency_links.txt
enfrosp_enmapboxapp.egg-info/not-zip-safe
enfrosp_enmapboxapp.egg-info/requires.txt
enfrosp_enmapboxapp.egg-info/top_level.txt