Metadata-Version: 2.4
Name: enfrosp_enmapboxapp
Version: 0.2.0
Summary: A graphical user interface for EnFROSP as an add-in for the EnMAP-Box QGIS plugin
Author-email: Daniel Scheffler <daniel.scheffler@gfz.de>
License-Expression: GPL-3.0-or-later
Project-URL: Source code, https://git.gfz.de/EnMAP/GFZ_Tools_EnMAP_BOX/enfrosp_enmapboxapp
Project-URL: Issue Tracker, https://git.gfz.de/EnMAP/GFZ_Tools_EnMAP_BOX/enfrosp_enmapboxapp/-/issues
Project-URL: Documentation, https://enmap.git-pages.gfz-potsdam.de/GFZ_Tools_EnMAP_BOX/enfrosp_enmapboxapp/doc/
Project-URL: Change log, https://enmap.git-pages.gfz-potsdam.de/GFZ_Tools_EnMAP_BOX/enfrosp_enmapboxapp/doc/history.html
Keywords: EnMAP,snow,retrieval,hyperspectral,remote sensing,satellite
Classifier: Development Status :: 3 - Alpha
Classifier: Intended Audience :: Science/Research
Classifier: Topic :: Scientific/Engineering
Classifier: Natural Language :: English
Classifier: Programming Language :: Python :: 3.10
Classifier: Programming Language :: Python :: 3.11
Classifier: Programming Language :: Python :: 3.12
Classifier: Programming Language :: Python :: 3.13
Classifier: Programming Language :: Python :: 3.14
Requires-Python: >=3.10
License-File: LICENSE
License-File: AUTHORS.rst
Requires-Dist: enfrosp
Requires-Dist: packaging
Requires-Dist: psutil
Provides-Extra: doc
Requires-Dist: sphinx>=4.1.1; extra == "doc"
Requires-Dist: sphinx-argparse; extra == "doc"
Requires-Dist: sphinx_rtd_theme; extra == "doc"
Requires-Dist: sphinx-autodoc-typehints; extra == "doc"
Requires-Dist: numpydoc>=1.7; extra == "doc"
Provides-Extra: test
Requires-Dist: pytest>=3; extra == "test"
Requires-Dist: pytest-cov; extra == "test"
Requires-Dist: pytest-reporter-html1; extra == "test"
Requires-Dist: urlchecker; extra == "test"
Provides-Extra: lint
Requires-Dist: flake8; extra == "lint"
Requires-Dist: pycodestyle; extra == "lint"
Requires-Dist: pydocstyle; extra == "lint"
Provides-Extra: deploy
Requires-Dist: build; extra == "deploy"
Requires-Dist: twine; extra == "deploy"
Provides-Extra: dev
Requires-Dist: enfrosp_enmapboxapp[test]; extra == "dev"
Requires-Dist: enfrosp_enmapboxapp[doc]; extra == "dev"
Requires-Dist: enfrosp_enmapboxapp[lint]; extra == "dev"
Requires-Dist: enfrosp_enmapboxapp[deploy]; extra == "dev"
Dynamic: license-file
